ids_peak/__init__.py
ids_peak/_ids_peak_ipl_python_extension.so
ids_peak/_ids_peak_python_interface.so
ids_peak/exceptions.py
ids_peak/ids_peak.py
ids_peak/ids_peak_ipl_extension.py
ids_peak/image_view.py
ids_peak/libFirmwareUpdate_gcc49_v3_4.so
ids_peak/libGCBase_gcc49_v3_4.so
ids_peak/libGenApi_gcc49_v3_4.so
ids_peak/libLog_gcc49_v3_4.so
ids_peak/libMathParser_gcc49_v3_4.so
ids_peak/libNodeMapData_gcc49_v3_4.so
ids_peak/libXmlParser_gcc49_v3_4.so
ids_peak/libids_peak.so
ids_peak/liblog4cpp_gcc49_v3_4.so
ids_peak-1.13.0.0.6.dist-info/METADATA
ids_peak-1.13.0.0.6.dist-info/WHEEL
ids_peak-1.13.0.0.6.dist-info/top_level.txt
ids_peak-1.13.0.0.6.dist-info/RECORD
ids_peak-1.13.0.0.6.dist-info/licenses/LICENSE
ids_peak-1.13.0.0.6.dist-info/licenses/third_party_copyrights.txt
ids_peak-1.13.0.0.6.dist-info/licenses/third_party_licenses.txt
