Metadata-Version: 2.4
Name: ids-peak
Version: 1.13.0.0.6
Summary: ids_peak - A library for device communication
Author-email: IDS Imaging Development Systems GmbH <support@ids-imaging.com>
License: Proprietary
Project-URL: Homepage, https://www.ids-imaging.com
Classifier: Programming Language :: Python :: 3
Classifier: Topic :: Multimedia :: Graphics :: Capture :: Digital Camera
Classifier: Topic :: Multimedia :: Video
Requires-Python: >=3.10
License-File: LICENSE
License-File: third_party_licenses.txt
License-File: third_party_copyrights.txt
Requires-Dist: ids_peak_ipl<2,>=1.17.1.0
Requires-Dist: ids_peak_common<2,>=1.1.0.0
Dynamic: license-file
